pytextcon/__init__.py
pytextcon/pytextcon.py
pytextcon-0.1.6.dist-info/LICENSE
pytextcon-0.1.6.dist-info/METADATA
pytextcon-0.1.6.dist-info/WHEEL
pytextcon-0.1.6.dist-info/top_level.txt
pytextcon-0.1.6.dist-info/RECORD
