Metadata-Version: 2.1
Name: pytextcon
Version: 0.1.6
Summary: Simple package to change the text color, text emphasis, and background color of print statements to the console.
Author-email: Michael <michael.lokrosh@gmail.com>
Project-URL: GitHub, https://github.com/Lokrosh/pytextcon
Keywords: print,color,console,text,formatting,emphasis,underline,bright
Classifier: Programming Language :: Python :: 3
Classifier: License :: OSI Approved :: MIT License
Classifier: Operating System :: OS Independent
Requires-Python: >=3.7
License-File: LICENSE
